<?xml version="1.0" encoding="GB2312"?>
<!-- Polynesia -->
<Civ4GameText xmlns="http://www.firaxis.com">
  <TEXT>
    <Tag>TXT_KEY_CIV_POLYNESIA_DESC</Tag>
    <English>The Polynesians</English>
    <L1 />
    <L2 />
    <L3 />
    <L4 />
    <Chinese>The Polynesians</Chinese>
  </TEXT>
  <TEXT>
    <Tag>TXT_KEY_CIV_POLYNESIA_PEOPLES</Tag>
    <English>Polynesian Peoples</English>
    <L1 />
    <L2 />
    <L3 />
    <L4 />
    <Chinese>Polynesian Peoples</Chinese>
  </TEXT>
  <TEXT>
    <Tag>TXT_KEY_CIV_POLYNESIA_DEFAULT</Tag>
    <English>Kingdom of %s1</English>
    <L1 />
    <L2 />
    <L3 />
    <L4 />
    <Chinese>Kingdom of %s1</Chinese>
  </TEXT>
  <TEXT>
    <Tag>TXT_KEY_CIV_POLYNESIA_REPUBLIC</Tag>
    <English>Polynesian Republics</English>
    <L1 />
    <L2 />
    <L3 />
    <L4 />
    <Chinese>Polynesian Republics</Chinese>
  </TEXT>
  <TEXT>
    <Tag>TXT_KEY_CIV_POLYNESIA_FASCIST</Tag>
    <English>Oceania</English>
    <L1 />
    <L2 />
    <L3 />
    <L4 />
    <Chinese>Oceania</Chinese>
  </TEXT>
  <TEXT>
    <Tag>TXT_KEY_CIV_POLYNESIA_TONGA</Tag>
    <English>Tonga</English>
    <L1 />
    <L2 />
    <L3 />
    <L4 />
    <Chinese>Tonga</Chinese>
  </TEXT>
  <TEXT>
    <Tag>TXT_KEY_CIV_POLYNESIA_TUI_TONGA</Tag>
    <English>Tu'i Tonga</English>
    <L1 />
    <L2 />
    <L3 />
    <L4 />
    <Chinese>Tu'i Tonga</Chinese>
  </TEXT>
  <TEXT>
    <Tag>TXT_KEY_CIV_POLYNESIA_HAWAII</Tag>
    <English>Hawaii</English>
    <L1 />
    <L2 />
    <L3 />
    <L4 />
    <Chinese>Hawaii</Chinese>
  </TEXT>
  <TEXT>
    <Tag>TXT_KEY_CIV_POLYNESIA_SAMOA</Tag>
    <English>Samoa</English>
    <L1 />
    <L2 />
    <L3 />
    <L4 />
    <Chinese>Samoa</Chinese>
  </TEXT>
  <TEXT>
    <Tag>TXT_KEY_CIV_POLYNESIA_TUI_MANUA</Tag>
    <English>Tu'i Manu'a</English>
    <L1 />
    <L2 />
    <L3 />
    <L4 />
    <Chinese>Tu'i Manu'a</Chinese>
  </TEXT>
  <TEXT>
    <Tag>TXT_KEY_CIV_POLYNESIA_NIUE</Tag>
    <English>Niue</English>
    <L1 />
    <L2 />
    <L3 />
    <L4 />
    <Chinese>Niue</Chinese>
  </TEXT>
  <TEXT>
    <Tag>TXT_KEY_CIV_POLYNESIA_TAHITI</Tag>
    <English>Tahiti</English>
    <L1 />
    <L2 />
    <L3 />
    <L4 />
    <Chinese>Tahiti</Chinese>
  </TEXT>
  <TEXT>
    <Tag>TXT_KEY_CIV_POLYNESIA_ADJECTIVE</Tag>
    <English>Polynesian</English>
    <L1 />
    <L2 />
    <L3 />
    <L4 />
    <Chinese>²¨ÀûÄáÎ÷ÑÇ</Chinese>
  </TEXT>
  <TEXT>
    <Tag>TXT_KEY_CIV_POLYNESIA_SHORT_DESC</Tag>
    <English>Polynesia</English>
    <L1 />
    <L2 />
    <L3 />
    <L4 />
    <Chinese>Polynesia</Chinese>
  </TEXT>
</Civ4GameText>